packagepoa/__init__.py
packagepoa/conf.py
packagepoa/decapitate_pdf.py
packagepoa/transform.py
packagepoa-0.3.0.dist-info/LICENSE
packagepoa-0.3.0.dist-info/METADATA
packagepoa-0.3.0.dist-info/WHEEL
packagepoa-0.3.0.dist-info/top_level.txt
packagepoa-0.3.0.dist-info/RECORD
