Metadata-Version: 2.1
Name: packagepoa
Version: 0.3.0
Summary: Generate, transform and assemble files for a PoA article.
Home-page: https://github.com/elifesciences/package-poa
Maintainer: eLife Sciences Publications Ltd.
Maintainer-email: tech-team@elifesciences.org
License: MIT
Classifier: Development Status :: 3 - Alpha
Classifier: Intended Audience :: Developers
Classifier: License :: OSI Approved :: MIT License
Classifier: Programming Language :: Python :: 3
License-File: LICENSE
Requires-Dist: configparser
